jsongraph/__init__.py
jsongraph/binding.py
jsongraph/common.py
jsongraph/config.py
jsongraph/context.py
jsongraph/graph.py
jsongraph/metadata.py
jsongraph/query.py
jsongraph/reflect.py
jsongraph/triplify.py
jsongraph/util.py
jsongraph/vocab.py
jsongraph/schemas/config.json
jsongraph-0.2.2.dist-info/DESCRIPTION.rst
jsongraph-0.2.2.dist-info/METADATA
jsongraph-0.2.2.dist-info/RECORD
jsongraph-0.2.2.dist-info/WHEEL
jsongraph-0.2.2.dist-info/metadata.json
jsongraph-0.2.2.dist-info/namespace_packages.txt
jsongraph-0.2.2.dist-info/top_level.txt
tests/__init__.py
tests/test_context.py
tests/test_graph.py
tests/test_metadata.py
tests/test_query.py
tests/test_reflect.py
tests/util.py
