Metadata-Version: 2.0
Name: jsongraph
Version: 0.2.2
Summary: Library for data integration using a JSON/RDF object graph.
Home-page: http://github.com/pudo/jsongraph
Author: Friedrich Lindenberg
Author-email: friedrich@pudo.org
License: MIT
Keywords: schema jsonschema json rdf graph sna networks
Platform: UNKNOWN
Classifier: Development Status :: 3 - Alpha
Classifier: Intended Audience :: Developers
Classifier: License :: OSI Approved :: MIT License
Classifier: Operating System :: OS Independent
Classifier: Programming Language :: Python :: 2.6
Classifier: Programming Language :: Python :: 2.7
Classifier: Programming Language :: Python :: 3.3
Classifier: Programming Language :: Python :: 3.4
Requires-Dist: jsonmapping
Requires-Dist: jsonschema
Requires-Dist: mqlparser
Requires-Dist: normality
Requires-Dist: pyyaml
Requires-Dist: rdflib
Requires-Dist: requests (>=2.0)
Requires-Dist: six
Requires-Dist: sparqlquery
Requires-Dist: url
